generic_elasticsearch/__init__.py
generic_elasticsearch/api/__init__.py
generic_elasticsearch/api/elasticsearch_api.py
generic_elasticsearch/api_client.py
generic_elasticsearch/configuration.py
generic_elasticsearch/exceptions.py
generic_elasticsearch/models/__init__.py
generic_elasticsearch/models/http_validation_error.py
generic_elasticsearch/models/insert.py
generic_elasticsearch/models/operation_result.py
generic_elasticsearch/models/query.py
generic_elasticsearch/models/search_result_hit_item.py
generic_elasticsearch/models/search_result_hits.py
generic_elasticsearch/models/search_results.py
generic_elasticsearch/models/validation_error.py
generic_elasticsearch/rest.py
pi_team_generic_es_client-1.1.2.dist-info/WHEEL
pi_team_generic_es_client-1.1.2.dist-info/METADATA
pi_team_generic_es_client-1.1.2.dist-info/RECORD
